Metadata-Version: 2.1
Name: sentry-dingtalk-tmp
Version: 2
Summary: sentry-dingtalk
Home-page: https://git.17bdc.com/android-apps/sentry-dingtalk
Author: Henryhaoson
Author-email: guonh <guoneihui@126.com>
License: MIT
Project-URL: Homepage, https://github.com/pypa/sampleproject
Project-URL: Bug Tracker, https://github.com/pypa/sampleproject/issues
Keywords: sentry dingtalk
Classifier: Programming Language :: Python :: 3
Classifier: License :: OSI Approved :: MIT License
Classifier: Operating System :: OS Independent
Requires-Python: >=3.6.13
License-File: LICENSE
Requires-Dist: sentry (>=21.5.1)
